geonomics/__init__.py
geonomics/main.py
geonomics/version.py
geonomics/data/IBD_IBE_demo/MMRR.R
geonomics/data/IBD_IBE_demo/MMRR.py
geonomics/data/IBD_IBE_demo/env.csv
geonomics/data/IBD_IBE_demo/gen.csv
geonomics/data/IBD_IBE_demo/geo.csv
geonomics/data/IBD_IBE_demo/run_mantel.R
geonomics/data/IBD_IBE_demo/run_partial_mantel.R
geonomics/data/IBD_IBE_demo/__pycache__/MMRR.cpython-38.pyc
geonomics/data/IBD_IBE_demo/__pycache__/MMRR.cpython-39.pyc
geonomics/data/default_models/selection_params.py
geonomics/data/yosemite_demo/yosemite_DEM_90x90.tif
geonomics/data/yosemite_demo/yosemite_lyrs/ppt_1980-2010_90x90.tif
geonomics/data/yosemite_demo/yosemite_lyrs/sdm_1980-2010_90x90.tif
geonomics/data/yosemite_demo/yosemite_lyrs/tmp_1980-2010_90x90.tif
geonomics/data/yosemite_demo/yosemite_lyrs/ppt/509_ppt_2015_90x90.tif
geonomics/data/yosemite_demo/yosemite_lyrs/ppt/514_ppt_2020_90x90.tif
geonomics/data/yosemite_demo/yosemite_lyrs/ppt/519_ppt_2025_90x90.tif
geonomics/data/yosemite_demo/yosemite_lyrs/ppt/524_ppt_2030_90x90.tif
geonomics/data/yosemite_demo/yosemite_lyrs/ppt/529_ppt_2035_90x90.tif
geonomics/data/yosemite_demo/yosemite_lyrs/ppt/534_ppt_2040_90x90.tif
geonomics/data/yosemite_demo/yosemite_lyrs/ppt/539_ppt_2045_90x90.tif
geonomics/data/yosemite_demo/yosemite_lyrs/ppt/544_ppt_2050_90x90.tif
geonomics/data/yosemite_demo/yosemite_lyrs/ppt/549_ppt_2055_90x90.tif
geonomics/data/yosemite_demo/yosemite_lyrs/ppt/554_ppt_2060_90x90.tif
geonomics/data/yosemite_demo/yosemite_lyrs/ppt/559_ppt_2065_90x90.tif
geonomics/data/yosemite_demo/yosemite_lyrs/ppt/564_ppt_2070_90x90.tif
geonomics/data/yosemite_demo/yosemite_lyrs/ppt/569_ppt_2075_90x90.tif
geonomics/data/yosemite_demo/yosemite_lyrs/ppt/574_ppt_2080_90x90.tif
geonomics/data/yosemite_demo/yosemite_lyrs/ppt/579_ppt_2085_90x90.tif
geonomics/data/yosemite_demo/yosemite_lyrs/ppt/584_ppt_2090_90x90.tif
geonomics/data/yosemite_demo/yosemite_lyrs/ppt/589_ppt_2095_90x90.tif
geonomics-1.4.9.dist-info/LICENSE.txt
geonomics-1.4.9.dist-info/METADATA
geonomics-1.4.9.dist-info/WHEEL
geonomics-1.4.9.dist-info/top_level.txt
geonomics-1.4.9.dist-info/RECORD
