Metadata-Version: 2.1
Name: geonomics
Version: 1.4.9
Summary: A package for landscape genomic simulation
Home-page: https://github.com/drewhart/geonomics
Download-URL: https://github.com/drewhart/geonomics/archive/1.4.9.tar.gz
Author: Drew Ellison Hart
Author-email: drew.ellison.hart@gmail.com
Project-URL: Documentation, https://htmlpreview.github.io/?https://github.com/drewhart/geonomics/blob/master/doc/built/doc.html
Project-URL: Methods Paper, https://doi.org/10.1093/molbev/msab175
Project-URL: Source, https://github.com/drewhart/geonomics
Keywords: landscape genomics genetics ecology evolution simulation model environmental model agent-based
Classifier: Programming Language :: Python :: 3
Classifier: License :: OSI Approved :: MIT License
Classifier: Operating System :: OS Independent
Classifier: Intended Audience :: Science/Research
Classifier: Intended Audience :: Education
Classifier: Natural Language :: English
Classifier: Topic :: Scientific/Engineering :: Bio-Informatics
Requires-Python: >=3.6
License-File: LICENSE.txt
Provides-Extra: 3d_plots_for_yosemite_demo
Requires-Dist: pykrige ; extra == '3d_plots_for_yosemite_demo'
Provides-Extra: simulation_on_neutral_landscape_models
Requires-Dist: nlmpy ; extra == 'simulation_on_neutral_landscape_models'
